MergeSourceFile/__init__.py
MergeSourceFile/main.py
mergesourcefile-1.2.0.dist-info/licenses/LICENSE
mergesourcefile-1.2.0.dist-info/METADATA
mergesourcefile-1.2.0.dist-info/WHEEL
mergesourcefile-1.2.0.dist-info/entry_points.txt
mergesourcefile-1.2.0.dist-info/top_level.txt
mergesourcefile-1.2.0.dist-info/RECORD
