Metadata-Version: 2.4
Name: MergeSourceFile
Version: 1.2.0
Summary: A Python tool to process SQL*Plus scripts with Jinja2 template support, resolving file inclusions (@, @@) and variable substitutions (DEFINE/UNDEFINE)
Author: Alejandro G.
License: MIT
Project-URL: Homepage, https://github.com/alegorico/MergeSourceFile
Project-URL: Repository, https://github.com/alegorico/MergeSourceFile
Project-URL: Issues, https://github.com/alegorico/MergeSourceFile/issues
Keywords: sqlplus,sql,oracle,script-processor,file-merger
Classifier: Development Status :: 5 - Production/Stable
Classifier: Intended Audience :: Developers
Classifier: Intended Audience :: System Administrators
Classifier: Operating System :: OS Independent
Classifier: Programming Language :: Python :: 3
Classifier: Programming Language :: Python :: 3.8
Classifier: Programming Language :: Python :: 3.9
Classifier: Programming Language :: Python :: 3.10
Classifier: Programming Language :: Python :: 3.11
Classifier: Programming Language :: Python :: 3.12
Classifier: Topic :: Database
Classifier: Topic :: Software Development :: Build Tools
Classifier: Topic :: Utilities
Requires-Python: >=3.8
License-File: LICENSE
Requires-Dist: jinja2>=3.0.0
Requires-Dist: tomli>=1.2.0; python_version < "3.11"
Provides-Extra: dev
Requires-Dist: build>=1.0.0; extra == "dev"
Requires-Dist: twine>=4.0.0; extra == "dev"
Requires-Dist: setuptools>=75.0.0; extra == "dev"
Requires-Dist: wheel>=0.40.0; extra == "dev"
Requires-Dist: pytest>=7.0.0; extra == "dev"
Requires-Dist: pytest-cov>=4.0.0; extra == "dev"
Requires-Dist: pytest-mock>=3.10.0; extra == "dev"
Provides-Extra: build
Requires-Dist: pyinstaller>=5.0.0; extra == "build"
Dynamic: license-file
